raylib_example_game/__init__.py
raylib_example_game/__main__.py
raylib_example_game/ending_screen.py
raylib_example_game/game.py
raylib_example_game/gameplay_screen.py
raylib_example_game/logo_screen.py
raylib_example_game/options_screen.py
raylib_example_game/screens.py
raylib_example_game/title_screen.py
raylib_example_game/resources/coin.wav
raylib_example_game/resources/mecha.png
raylib_example_game/resources/music.ogg
raylib_example_game/resources/wabbit_alpha.png
raylib_example_game-0.3.1.dist-info/METADATA
raylib_example_game-0.3.1.dist-info/WHEEL
raylib_example_game-0.3.1.dist-info/entry_points.txt
raylib_example_game-0.3.1.dist-info/licenses/LICENSE
raylib_example_game-0.3.1.dist-info/RECORD
