Metadata-Version: 2.4
Name: raylib-example-game
Version: 0.3.1
Summary: A simple game example using Raylib Python bindings
Project-URL: Homepage, https://github.com/electronstudio/raylib-example-game
Project-URL: Repository, https://github.com/electronstudio/raylib-example-game.git
Project-URL: Issues, https://github.com/electronstudio/raylib-example-game/issues
Author-email: Electron Studio <github@electronstudio.co.uk>
License: Copyright (c) 2025 Electron Studio
License-File: LICENSE
Keywords: game,raylib
Classifier: Development Status :: 3 - Alpha
Classifier: Intended Audience :: Developers
Classifier: License :: OSI Approved :: MIT License
Classifier: Programming Language :: Python :: 3
Classifier: Programming Language :: Python :: 3.11
Classifier: Topic :: Games/Entertainment
Classifier: Topic :: Software Development :: Libraries :: Python Modules
Requires-Python: >=3.11
Requires-Dist: raylib-sdl>=5.5.0.3
